{"status":0,"count":3,
    "data":[
    {"id":1,"user_name":"zs","content":"能和心爱的人一起睡觉，是件幸福的事情；可是，打呼噜怎么办？","add_time":"2018-08-23 12:34:25"},
    {"id":2,"user_name":"晨曦","content":"想要这样一间小木屋，夏天挫冰吃瓜，冬天围炉取暖.","add_time":"2018-05-23 12:34:25"},
    {"id":3,"user_name":"赵六","content":"烤炉模式的城，到黄昏，如同打翻的调色盘一般","add_time":"2018-04-21 12:34:25"},
    {"id":4,"user_name":"邓伦","content":"幸福","add_time":"2017-08-23 12:34:25"},
    {"id":5,"user_name":"小绵羊","content":"木屋","add_time":"2017-05-23 12:34:25"},
    {"id":6,"user_name":"二月红","content":"CBD","add_time":"2017-04-21 12:34:25"}
    
]}